odoo/addons/base_suspend_security/README.rst
odoo/addons/base_suspend_security/__init__.py
odoo/addons/base_suspend_security/__manifest__.py
odoo/addons/base_suspend_security/base_suspend_security.py
odoo/addons/base_suspend_security/i18n/ar.po
odoo/addons/base_suspend_security/i18n/base_suspend_security.pot
odoo/addons/base_suspend_security/i18n/ca.po
odoo/addons/base_suspend_security/i18n/da.po
odoo/addons/base_suspend_security/i18n/de.po
odoo/addons/base_suspend_security/i18n/el_GR.po
odoo/addons/base_suspend_security/i18n/en.po
odoo/addons/base_suspend_security/i18n/es.po
odoo/addons/base_suspend_security/i18n/es_ES.po
odoo/addons/base_suspend_security/i18n/es_MX.po
odoo/addons/base_suspend_security/i18n/fi.po
odoo/addons/base_suspend_security/i18n/fr.po
odoo/addons/base_suspend_security/i18n/fr_CA.po
odoo/addons/base_suspend_security/i18n/fr_CH.po
odoo/addons/base_suspend_security/i18n/fr_FR.po
odoo/addons/base_suspend_security/i18n/hr.po
odoo/addons/base_suspend_security/i18n/hr_HR.po
odoo/addons/base_suspend_security/i18n/it.po
odoo/addons/base_suspend_security/i18n/nl.po
odoo/addons/base_suspend_security/i18n/nl_NL.po
odoo/addons/base_suspend_security/i18n/pt.po
odoo/addons/base_suspend_security/i18n/pt_BR.po
odoo/addons/base_suspend_security/i18n/pt_PT.po
odoo/addons/base_suspend_security/i18n/ro.po
odoo/addons/base_suspend_security/i18n/sl.po
odoo/addons/base_suspend_security/i18n/tr.po
odoo/addons/base_suspend_security/i18n/tr_TR.po
odoo/addons/base_suspend_security/i18n/zh_CN.po
odoo/addons/base_suspend_security/models/__init__.py
odoo/addons/base_suspend_security/models/base.py
odoo/addons/base_suspend_security/models/ir_model_access.py
odoo/addons/base_suspend_security/models/ir_rule.py
odoo/addons/base_suspend_security/models/res_users.py
odoo/addons/base_suspend_security/readme/CONTRIBUTORS.rst
odoo/addons/base_suspend_security/readme/DESCRIPTION.rst
odoo/addons/base_suspend_security/readme/INSTALL.rst
odoo12_addon_base_suspend_security-12.0.1.0.4.dist-info/METADATA
odoo12_addon_base_suspend_security-12.0.1.0.4.dist-info/WHEEL
odoo12_addon_base_suspend_security-12.0.1.0.4.dist-info/top_level.txt
odoo12_addon_base_suspend_security-12.0.1.0.4.dist-info/RECORD
